{"kind":"FileIndex","apiVersion":"v1","Files":{".gitignore":{"Size":400,"LastModifiedDate":"2024-06-02T18:40:15.034908408-04:00"},".odoignore":{"Size":34,"LastModifiedDate":"2024-06-02T19:47:53.635147095-04:00"},"devfile.yaml":{"Size":1813,"LastModifiedDate":"2024-06-03T17:13:56.407858404-04:00"},"pom.xml":{"Size":1226,"LastModifiedDate":"2024-06-03T17:07:21.190352404-04:00"},"src":{"Size":30,"LastModifiedDate":"2024-06-02T17:33:35-04:00"},"src/main":{"Size":35,"LastModifiedDate":"2024-06-02T17:33:35-04:00"},"src/main/java":{"Size":17,"LastModifiedDate":"2024-06-02T17:33:35-04:00"},"src/main/java/com":{"Size":21,"LastModifiedDate":"2024-06-02T17:33:35-04:00"},"src/main/java/com/example":{"Size":18,"LastModifiedDate":"2024-06-02T17:33:35-04:00"},"src/main/java/com/example/demo":{"Size":34,"LastModifiedDate":"2024-06-03T17:06:59.830885911-04:00"},"src/main/java/com/example/demo/DemoApplication.java":{"Size":305,"LastModifiedDate":"2024-06-02T19:49:53.922201268-04:00"},"src/main/resources":{"Size":36,"LastModifiedDate":"2024-06-04T06:04:36.895592069-04:00"},"src/main/resources/application.properties":{"Size":34,"LastModifiedDate":"2024-06-04T06:04:36.881591766-04:00"},"src/test":{"Size":18,"LastModifiedDate":"2024-06-02T17:33:35-04:00"},"src/test/java":{"Size":17,"LastModifiedDate":"2024-06-02T17:33:35-04:00"},"src/test/java/com":{"Size":21,"LastModifiedDate":"2024-06-02T17:33:35-04:00"},"src/test/java/com/example":{"Size":18,"LastModifiedDate":"2024-06-02T17:33:35-04:00"},"src/test/java/com/example/demo":{"Size":39,"LastModifiedDate":"2024-06-02T17:33:35-04:00"},"src/test/java/com/example/demo/DemoApplicationTests.java":{"Size":206,"LastModifiedDate":"2024-06-02T17:33:35-04:00"},"target":{"Size":209,"LastModifiedDate":"2024-06-03T17:07:39.521752767-04:00"},"target/classes":{"Size":47,"LastModifiedDate":"2024-06-03T17:07:38.287725815-04:00"},"target/classes/application.properties":{"Size":33,"LastModifiedDate":"2024-06-03T17:07:37.303704324-04:00"},"target/classes/com":{"Size":21,"LastModifiedDate":"2024-06-03T17:07:38.287725815-04:00"},"target/classes/com/example":{"Size":18,"LastModifiedDate":"2024-06-03T17:07:38.287725815-04:00"},"target/classes/com/example/demo":{"Size":35,"LastModifiedDate":"2024-06-03T17:07:38.287725815-04:00"},"target/classes/com/example/demo/DemoApplication.class":{"Size":733,"LastModifiedDate":"2024-06-03T17:07:38.288725837-04:00"},"target/demo-0.0.1-SNAPSHOT.jar":{"Size":20265843,"LastModifiedDate":"2024-06-03T17:07:39.776758336-04:00"},"target/demo-0.0.1-SNAPSHOT.jar.original":{"Size":2612,"LastModifiedDate":"2024-06-03T17:07:39.221746214-04:00"},"target/generated-sources":{"Size":25,"LastModifiedDate":"2024-06-03T17:07:37.423706945-04:00"},"target/generated-sources/annotations":{"Size":6,"LastModifiedDate":"2024-06-03T17:07:37.423706945-04:00"},"target/generated-test-sources":{"Size":30,"LastModifiedDate":"2024-06-03T17:07:38.308726274-04:00"},"target/generated-test-sources/test-annotations":{"Size":6,"LastModifiedDate":"2024-06-03T17:07:38.308726274-04:00"},"target/maven-archiver":{"Size":28,"LastModifiedDate":"2024-06-03T17:07:39.147744598-04:00"},"target/maven-archiver/pom.properties":{"Size":59,"LastModifiedDate":"2024-06-03T17:07:39.147744598-04:00"},"target/maven-status":{"Size":35,"LastModifiedDate":"2024-06-03T17:07:37.41570677-04:00"},"target/maven-status/maven-compiler-plugin":{"Size":40,"LastModifiedDate":"2024-06-03T17:07:38.307726252-04:00"},"target/maven-status/maven-compiler-plugin/compile":{"Size":29,"LastModifiedDate":"2024-06-03T17:07:37.41570677-04:00"},"target/maven-status/maven-compiler-plugin/compile/default-compile":{"Size":52,"LastModifiedDate":"2024-06-03T17:07:38.291725902-04:00"},"target/maven-status/maven-compiler-plugin/compile/default-compile/createdFiles.lst":{"Size":39,"LastModifiedDate":"2024-06-03T17:07:38.292725924-04:00"},"target/maven-status/maven-compiler-plugin/compile/default-compile/inputFiles.lst":{"Size":61,"LastModifiedDate":"2024-06-03T17:07:37.417706814-04:00"},"target/maven-status/maven-compiler-plugin/testCompile":{"Size":33,"LastModifiedDate":"2024-06-03T17:07:38.307726252-04:00"},"target/maven-status/maven-compiler-plugin/testCompile/default-testCompile":{"Size":52,"LastModifiedDate":"2024-06-03T17:07:38.619733066-04:00"},"target/maven-status/maven-compiler-plugin/testCompile/default-testCompile/createdFiles.lst":{"Size":44,"LastModifiedDate":"2024-06-03T17:07:38.619733066-04:00"},"target/maven-status/maven-compiler-plugin/testCompile/default-testCompile/inputFiles.lst":{"Size":66,"LastModifiedDate":"2024-06-03T17:07:38.307726252-04:00"},"target/test-classes":{"Size":17,"LastModifiedDate":"2024-06-03T17:07:38.613732935-04:00"},"target/test-classes/com":{"Size":21,"LastModifiedDate":"2024-06-03T17:07:38.613732935-04:00"},"target/test-classes/com/example":{"Size":18,"LastModifiedDate":"2024-06-03T17:07:38.613732935-04:00"},"target/test-classes/com/example/demo":{"Size":40,"LastModifiedDate":"2024-06-03T17:07:38.613732935-04:00"},"target/test-classes/com/example/demo/DemoApplicationTests.class":{"Size":531,"LastModifiedDate":"2024-06-03T17:07:38.614732957-04:00"}}}